dagma/__init__.py
dagma/linear.py
dagma/locally_connected.py
dagma/nonlinear.py
dagma/utils.py
dagma-1.1.1.dist-info/LICENSE
dagma-1.1.1.dist-info/METADATA
dagma-1.1.1.dist-info/WHEEL
dagma-1.1.1.dist-info/top_level.txt
dagma-1.1.1.dist-info/RECORD
