Metadata-Version: 2.1
Name: dagma
Version: 1.1.1
Summary: Implementation of the DAGMA algorithm
Author-email: Kevin Bello <kbello@cs.cmu.edu>
License: Apache 2.0
Project-URL: Repository, https://github.com/kevinsbello/dagma
Project-URL: Documentation, https://dagma.readthedocs.io/en/latest/
Project-URL: Issues, https://github.com/kevinsbello/dagma/issues
Keywords: dagma,notears,causal discovery,bayesian network,structure learning
Classifier: Programming Language :: Python :: 3
Classifier: License :: OSI Approved :: Apache Software License
Classifier: Operating System :: OS Independent
Classifier: Topic :: Scientific/Engineering :: Artificial Intelligence
Classifier: Intended Audience :: Science/Research
Classifier: Development Status :: 3 - Alpha
Requires-Python: >=3.7
License-File: LICENSE
Requires-Dist: numpy
Requires-Dist: scipy
Requires-Dist: torch
Requires-Dist: tqdm
Requires-Dist: igraph
